fovsa_cli/__init__.py
fovsa_cli/cli.py
fovsa_cli/fovsa_cli.py
fovsa_cli-0.0.5.dist-info/AUTHORS.rst
fovsa_cli-0.0.5.dist-info/LICENSE
fovsa_cli-0.0.5.dist-info/METADATA
fovsa_cli-0.0.5.dist-info/WHEEL
fovsa_cli-0.0.5.dist-info/top_level.txt
fovsa_cli-0.0.5.dist-info/RECORD
