Metadata-Version: 2.1
Name: fovsa_cli
Version: 0.0.5
Summary: CLI Tool for Fovsa App
Author-email: Ahmet Can IŞIK <imcanisik@gmail.com>
Maintainer-email: Ahmet Can IŞIK <imcanisik@gmail.com>
License: MIT license
Project-URL: bugs, https://github.com/ahmetcanisik/fovsa_cli/issues
Project-URL: changelog, https://github.com/ahmetcanisik/fovsa_cli/blob/master/changelog.md
Project-URL: homepage, https://github.com/ahmetcanisik/fovsa_cli
License-File: LICENSE
License-File: AUTHORS.rst
Requires-Dist: typer
Provides-Extra: dev
Requires-Dist: coverage; extra == "dev"
Requires-Dist: mypy; extra == "dev"
Requires-Dist: pytest; extra == "dev"
Requires-Dist: ruff; extra == "dev"
